sonic_cd-1.0.0rc39.data/scripts/sonic
sonic_cd-1.0.0rc39.data/scripts/sonic-context
soniclib/__init__.py
soniclib/compose.py
soniclib/config.py
soniclib/context.py
soniclib/exceptions.py
soniclib/filelock.py
soniclib/logpipe.py
soniclib/logutils.py
soniclib/metrics.py
soniclib/sonic.py
soniclib/util.py
soniclib/resources/config.yml
soniclib/resources/cygwin/config.yml
sonic_cd-1.0.0rc39.dist-info/LICENSE.md
sonic_cd-1.0.0rc39.dist-info/METADATA
sonic_cd-1.0.0rc39.dist-info/WHEEL
sonic_cd-1.0.0rc39.dist-info/top_level.txt
sonic_cd-1.0.0rc39.dist-info/RECORD
