Metadata-Version: 2.1
Name: sonic-cd
Version: 1.0.0rc39
Summary: UNKNOWN
Home-page: UNKNOWN
Author: Tomas Riha
Author-email: tomas.riha@wirelesscar.com
License: UNKNOWN
Platform: UNKNOWN
Requires-Dist: awscli (>=1.16.118)
Requires-Dist: PyYAML (<=3.13,>=3.10)
Requires-Dist: boto3 (>=1.9.108)
Requires-Dist: botocore (>=1.12.108)
Requires-Dist: sh (>=1.12.14)
Requires-Dist: python-json-logger (>=0.1.8)
Requires-Dist: validators (>=0.12.4)
